{"updated_at": "2026-03-22T17:40:01.689730-04:00", "scores": {"4c7ca31e0fd6a4e5eb69fa8177182cfc": {"away": 69, "home": 79, "completed": true, "last_update": ""}, "7dd1f585b9d94dff98991f333edc5267": {"away": 63, "home": 82, "completed": true, "last_update": ""}, "dc00ee0e46d8ae7b831e27222372c8f2": {"away": 35, "home": 34, "completed": false, "last_update": "2026-03-22T17:40:01.444919"}, "38a957852d4e61b49d29915dcb7f4251": {"away": 14, "home": 6, "completed": false, "last_update": "2026-03-22T17:40:01.444919"}}}